{
  "title": "隐形的翅膀",
  "artist": "张韶涵",
  "album": "潘朵拉",
  "releaseDate": "2006-01-05",
  "lyrics": "[ti:隐形的翅膀 (《爱杀17》电视剧片尾曲)]\n[ar:张韶涵]\n[al:潘朵拉]\n[by:]\n[offset:0]\n隐形的翅膀 - 张韶涵 (Angela Zhang)\n词：王雅君\n曲：王雅君\n编曲：陈俊廷\n每一次\n都在徘徊孤单中坚强\n每一次\n\n就算很受伤 也不闪泪光\n我知道\n\n我一直有双隐形的翅膀\n带我飞\n\n飞过绝望\n\n不去想\n\n他们拥有美丽的太阳\n我看见\n\n每天的夕阳 也会有变化\n我知道\n\n我一直有双隐形的翅膀\n带我飞\n\n给我希望\n\n我终于 看到\n所有梦想都开花\n追逐的年轻\n歌声多嘹亮\n我终于 翱翔\n用心凝望不害怕\n哪里会有风\n就飞多远吧\n\n不去想\n\n他们拥有美丽的太阳\n我看见\n\n每天的夕阳 也会有变化\n我知道\n\n我一直有双隐形的翅膀\n带我飞\n\n给我希望\n\n我终于 看到\n所有梦想都开花\n追逐的年轻\n歌声多嘹亮\n\n我终于 翱翔\n\n用心凝望不害怕\n哪里会有风\n就飞多远吧\n\n隐形的翅膀\n让梦恒久比天长\n留一个 愿望\n让自己想象",
  "language": "中文",
  "cover": "张韶涵/潘朵拉/隐形的翅膀.jpg",
  "sourceUrl": "https://y.qq.com/n/ryqq/songDetail/004ZX0AQ49Bc8Y"
}