{
  "title": "你是我的风景",
  "artist": "何洁",
  "album": "想要回到 何洁",
  "releaseDate": "2010-09-08",
  "lyrics": "[ti:]\n[ar:]\n[al:]\n[by:天琴实验室AI生成v1.0]\n[offset:0]\n作词: 彭青\n作曲: 彭青\n一路过很多城市\n一路看很多人群\n匆匆忙忙地在行程里睡了又醒\n飘忽不定\n这也是一种麻痹\n直到我看到了你\n莽莽撞撞靠近\n每一个细节都牵引我放下行李\n让心自然的休息\n你就是我的风景\n云高风清\n不走下去\n停在这里\n视线里都是你\n全部是你微笑的表情\n爱让悬崖变平地\n生出森林\n一整片的森林\n你在树荫里\n复杂的生命\n因为有你\n我一层透明\n一路过很多城市\n一路看很多人群\n匆匆忙忙的在行程里睡了又醒\n飘忽不定\n这也是一种麻痹\n直到我看到了你\n莽莽撞撞靠近\n每一个细节都牵引我放下行李\n让心自然的休息\n你就是我的风景\n云高风清\n不走下去\n停在这里\n视线里都是你\n全部是你微笑的表情\n爱让悬崖变平地\n生出森林\n一整片的森林\n你在树荫里\n复杂的生命\n因为有你\n我一层透明\n你就是我的风景\n云高风清\n不走下去\n停在这里\n视线里都是你\n全部是你微笑的表情\n爱让悬崖变平地\n生出森林\n一整片的森林\n你在树荫里\n复杂的生命\n因为有你\n我一层透明",
  "language": "中文",
  "cover": "何洁/想要回到 何洁/你是我的风景.jpg",
  "sourceUrl": "https://y.qq.com/n/ryqq/songDetail/002mDPmy2IsAxe"
}