{
  "title": "告白气球",
  "artist": "周杰伦",
  "album": "周杰伦的床边故事",
  "releaseDate": "2016-06-23",
  "lyrics": "[ti:告白气球]\n[ar:周杰伦]\n[al:周杰伦的床边故事]\n[by:]\n[offset:0]\n告白气球 - 周杰伦 (Jay Chou)\n词：方文山\n曲：周杰伦\n编曲：林迈可\n塞纳河畔 左岸的咖啡\n我手一杯 品尝你的美\n\n留下唇印的嘴\n\n花店玫瑰 名字写错谁\n告白气球 风吹到对街\n\n微笑在天上飞\n\n你说你有点难追\n想让我知难而退\n礼物不需挑最贵\n只要香榭的落叶\n喔 营造浪漫的约会\n不害怕搞砸一切\n拥有你就拥有全世界\n\n亲爱的 爱上你\n从那天起\n\n甜蜜的很轻易\n\n亲爱的 别任性\n你的眼睛\n\n在说我愿意\n\n塞纳河畔 左岸的咖啡\n我手一杯 品尝你的美\n留下唇印的嘴\n\n花店玫瑰 名字写错谁\n告白气球 风吹到对街\n\n微笑在天上飞\n\n你说你有点难追\n想让我知难而退\n礼物不需挑最贵\n只要香榭的落叶\n喔 营造浪漫的约会\n不害怕搞砸一切\n拥有你就拥有 全世界\n\n亲爱的 爱上你\n从那天起\n\n甜蜜的很轻易\n\n亲爱的 别任性\n你的眼睛\n\n在说我愿意\n\n亲爱的 爱上你\n\n恋爱日记\n\n飘香水的回忆\n\n一整瓶 的梦境\n全都有你\n\n搅拌在一起\n\n亲爱的别任性\n你的眼睛\n\n在说我愿意",
  "language": "中文",
  "cover": "周杰伦/周杰伦的床边故事/告白气球.jpg",
  "sourceUrl": "https://y.qq.com/n/ryqq/songDetail/003OUlho2HcRHC"
}