{
  "title": "暁の車 (晓之车)",
  "artist": "南里侑香 (なんり ゆうか)",
  "album": "機動戦士ガンダム SEED スーツCD (4) ミゲル・アイマン×ニコル・アマルフィ (机动战士高达seed suit cd vol.4 miguel×nicol)",
  "releaseDate": "2003-06-20",
  "lyrics": "[ti:暁の車 (晓之车) (《机动战士高达seed》TV动画第38集插曲)]\n[ar:南里侑香 (なんり ゆうか)]\n[al:機動戦士ガンダム SEED スーツCD (4) ミゲル・アイマン×ニコル・アマルフィ (机动战士高达SEED SUIT CD vol.4 MIGUEL×NICOL)]\n[by:]\n[offset:0]\n[kana:1あかつき1くるま1なん1り1ゆう1か1し1かじ1うら1ゆ1き1きょく1かじ1うら1ゆ1き1かぜ1こ1かげ1うつぶ1な1み1し1わたし1わたし1み1ゆ1ひと1しら1かな1こ1ひと1なげ1ほし1お1い1さけ1はな1しず1ゆ1ひたい1のこ1て1き1おく1はる1び1やさ1て1こ1ども1こころ1も1くる1ま1ふ1はら1すす1ゆ1ひと1なげ1かな1むね1いと1はげ1か1な1かな1そ1しろ1はな1ゆ1なつ1かげ1ひたい1な1あか1そ1すな1はる1こ1い1おも1で1や1つ1すす1だい1ち1なつ1め1ぶ1い1あかつき1くるま1み1おく1はな1ゆ1いま1ど1こ1み1やす1よ1あ1いち1ど1て1け1ともし1び1くる1ま1まわ]\n暁の車 - 南里侑香 (なんり ゆうか)\n词：梶浦由記\n曲：梶浦由記\n風さそう木陰に俯せて泣いてる\n見も知らぬ私を私が見ていた\n逝く人の調べを奏でるギターラ\n来ぬ人の嘆きに星は落ちて\n行かないで どんなに叫んでも\nオレンジの花びら\n静かに揺れるだけ\nやわらかな額に残された\n手のひらの記憶遥か\nとこしえのさよならつま弾く\n優しい手にすがる子供の心を\n燃えさかる車輪は振り払い進む\n逝く人の嘆きを奏でてギターラ\n胸の糸激しく掻き鳴らして\n哀しみに染まらない白さで\nオレンジの花びら\n揺れてた夏の影に\nやわらかな額を失くしても\n赤く染めた砂遥か越えて行く\nさよならのリズム\n想い出を焼き尽くして進む大地に\n懐かしく\n芽吹いて行くものがあるの\n暁の車を見送って\nオレンジの花びら\n揺れてる今も何処か\nいつか見た安らかな夜明けを\nもう一度手にするまで\n消さないで灯火\n車輪は廻るよ",
  "language": "日语",
  "cover": "南里侑香 (なんり ゆうか)/機動戦士ガンダム SEED スーツCD (4) ミゲル・アイマン×ニコル・アマルフィ (机动战士高达seed suit cd vol.4 miguel×nicol)/暁の車 (晓之车).jpg",
  "sourceUrl": "https://y.qq.com/n/ryqq/songDetail/001xfNQW1cAVVM"
}