{
  "title": "夜奔",
  "artist": "黄诗扶",
  "album": "今日无事",
  "releaseDate": "2024-03-15",
  "lyrics": "[ti:夜奔]\n[ar:黄诗扶]\n[al:夜奔]\n[by:]\n[offset:0]\n夜奔 - 黄诗扶\n词：李开先\n曲：黄诗扶\n歌词编辑：黄诗扶/左木修\n编曲Arranger：Tureleon郭超\n吉他 Guitar：Tureleon郭超\n贝斯 Bass：Tureleon郭超\n弦乐Strings：国际首席爱乐乐团\n弦乐录音棚 Strings Recording Studio：金田录音棚\n弦乐录音师 Strings Recording：王小四\n弦乐监制Strings Producer：李朋\n和声编写 Backing Vocal Production：黄诗扶\n和声 Backing Vocal：黄诗扶/戈锐\n戏曲 Traditional Opera：李相凯\n录音 Recording：禾声稻场\n混音/母带 Mixing/Mastering：郑昊杰@2496 Topmusic\n混音棚 Mixing Studio：2496 Topmusic\n统筹 Coordinator：小羊\n制作人 Producer：黄诗扶/Tureleon郭超\nOP：黄诗扶工作室\nSP：万象凡音\n引用：歌词均节选整合自「明」·李开先 戏曲剧目《夜奔》\n数尽更筹 听残银漏\n回首望天朝\n急走忙逃 顾不得忠和孝\n凉夜迢迢 夜迢迢 遥瞻残月\n暗度重关 心忙忙 奔走荒郊\n身轻不惮路迢遥\n望家乡 去路遥\n叹英雄气怎消\n怀揣着雪刃刀\n急走羊肠去路遥\n望家乡 去路遥\n叹英雄气怎消\n怀揣着雪刃刀\n急走羊肠去路遥\n魄散魂消\n风吹落叶飘 深林震虎啸\n似龙驹奔逃 魂飞胆销\n汗淋如汤浇 心煎似火烧\n生死应难料 劬劳悲号\n似这鬓发焦灼\n行李萧条\n此一去博得个\n斗转天回\n海沸山摇\n数尽更筹 听残银漏\n回首望天朝\n急走忙逃 顾不得忠和孝\n凉夜迢迢 夜迢迢 遥瞻残月\n暗度重关 心忙忙 奔走荒郊\n身轻不惮路迢遥\n望家乡 去路遥\n叹英雄气怎消\n怀揣着雪刃刀\n急走羊肠去路遥\n望家乡 去路遥\n叹英雄气怎消\n怀揣着雪刃刀\n急走羊肠去路遥\n魄散魂消\n风吹落叶飘 深林震虎啸\n似龙驹奔逃 魂飞胆销\n汗淋如汤浇 心煎似火烧\n生死应难料 劬劳悲号\n似这鬓发焦灼\n行李萧条\n此一去博得个\n斗转天回\n海沸山摇\n风飒飒雨打打穿林啸\n乌压压起松梢\n顾不得风雨打度良宵\n挣残命一条",
  "language": "中文",
  "cover": "黄诗扶/今日无事/夜奔.jpg",
  "sourceUrl": "https://y.qq.com/n/ryqq/songDetail/004HjFGN0MTtBM"
}